goldencage
