Metadata-Version: 1.0
Name: goldencage
Version: 3.3
Summary: virtual coin & task management for mobile app (specially for china)
Home-page: https://github.com/jeffkit/goldencage
Author: jeff kit
Author-email: bbmyth@gmail.com
License: UNKNOWN
Platform: UNKNOWN
